django_e2ee/__init__.py
django_e2ee/_version.py
django_e2ee/admin.py
django_e2ee/app_settings.py
django_e2ee/apps.py
django_e2ee/context_processors.py
django_e2ee/forms.py
django_e2ee/models.py
django_e2ee/permissions.py
django_e2ee/py.typed
django_e2ee/serializers.py
django_e2ee/urls.py
django_e2ee/views.py
django_e2ee/migrations/0001_initial.py
django_e2ee/migrations/__init__.py
django_e2ee/static/js/e2ee/fill_random_password.js
django_e2ee/static/js/e2ee/password_generator.js
django_e2ee/static/js/e2ee/passwords.json
django_e2ee/static/js/e2ee/submit_form_as_json.js
django_e2ee/static/js/e2ee/utils.js
django_e2ee/templates/e2ee/serviceworker_routes.js
django_e2ee/templatetags/__init__.py
django_e2ee/templatetags/e2ee.py
django_e2ee/tests/__init__.py
django_e2ee/tests/test_models.py
django_e2ee/tests/test_views.py
django_e2ee_framework-0.0.1.dev3.dist-info/licenses/LICENSE
django_e2ee_framework-0.0.1.dev3.dist-info/METADATA
django_e2ee_framework-0.0.1.dev3.dist-info/WHEEL
django_e2ee_framework-0.0.1.dev3.dist-info/top_level.txt
django_e2ee_framework-0.0.1.dev3.dist-info/RECORD
