Metadata-Version: 2.4
Name: django-e2ee-framework
Version: 0.0.1.dev3
Summary: An end-to-end encryption framework for Django
Home-page: https://codebase.helmholtz.cloud/hcdc/django/django-e2ee-framework
Author: Philipp S. Sommer
Author-email: hcdc_support@hereon.de
License: EUPL-1.2
Project-URL: Documentation, https://django-e2ee-framework.readthedocs.io/en/latest/
Project-URL: Source, https://codebase.helmholtz.cloud/hcdc/django/django-e2ee-framework
Project-URL: Tracker, https://codebase.helmholtz.cloud/hcdc/django/django-e2ee-framework/-/issues
Keywords: e2ee,end-to-end-encryption,security,serviceworker,django,datahub,hifis,helmholtz
Classifier: Environment :: Web Environment
Classifier: Framework :: Django
Classifier: Framework :: Django :: 3.2
Classifier: Development Status :: 3 - Alpha
Classifier: Intended Audience :: Developers
Classifier: License :: OSI Approved :: European Union Public Licence 1.2 (EUPL 1.2)
Classifier: Operating System :: OS Independent
Classifier: Programming Language :: Python
Classifier: Programming Language :: Python :: 3
Classifier: Programming Language :: Python :: 3 :: Only
Classifier: Programming Language :: Python :: 3.7
Classifier: Programming Language :: Python :: 3.8
Classifier: Programming Language :: Python :: 3.9
Classifier: Programming Language :: Python :: 3.10
Classifier: Topic :: Internet :: WWW/HTTP
Classifier: Topic :: Internet :: WWW/HTTP :: Dynamic Content
Classifier: Typing :: Typed
Requires-Python: >=3.7
License-File: LICENSE
Requires-Dist: requests
Requires-Dist: Django<5.3,>=3.1
Requires-Dist: djangorestframework
Requires-Dist: cryptography
Provides-Extra: testsite
Requires-Dist: tox; extra == "testsite"
Requires-Dist: requests; extra == "testsite"
Requires-Dist: types-requests; extra == "testsite"
Requires-Dist: isort==7.0.0; extra == "testsite"
Requires-Dist: black==25.9.0; extra == "testsite"
Requires-Dist: blackdoc==0.4.5; extra == "testsite"
Requires-Dist: flake8==7.3.0; extra == "testsite"
Requires-Dist: pre-commit; extra == "testsite"
Requires-Dist: mypy==1.4.1; extra == "testsite"
Requires-Dist: django-stubs==4.2.3; extra == "testsite"
Requires-Dist: pytest-django; extra == "testsite"
Requires-Dist: pytest-cov; extra == "testsite"
Requires-Dist: selenium; extra == "testsite"
Provides-Extra: dev
Requires-Dist: tox; extra == "dev"
Requires-Dist: requests; extra == "dev"
Requires-Dist: types-requests; extra == "dev"
Requires-Dist: isort==7.0.0; extra == "dev"
Requires-Dist: black==25.9.0; extra == "dev"
Requires-Dist: blackdoc==0.4.5; extra == "dev"
Requires-Dist: flake8==7.3.0; extra == "dev"
Requires-Dist: pre-commit; extra == "dev"
Requires-Dist: mypy==1.4.1; extra == "dev"
Requires-Dist: django-stubs==4.2.3; extra == "dev"
Requires-Dist: pytest-django; extra == "dev"
Requires-Dist: pytest-cov; extra == "dev"
Requires-Dist: selenium; extra == "dev"
Requires-Dist: Sphinx; extra == "dev"
Requires-Dist: mde-sphinx-ext; extra == "dev"
Requires-Dist: django_redis; extra == "dev"
Requires-Dist: autodocsumm; extra == "dev"
Requires-Dist: sphinxcontrib-django; extra == "dev"
Dynamic: license-file
